LICENSE
MANIFEST.in
README.rst
setup.py
poco/__init__.py
poco/poco.py
poco/test/__init__.py
poco/test/test_poco.py
python_poco.egg-info/PKG-INFO
python_poco.egg-info/SOURCES.txt
python_poco.egg-info/dependency_links.txt
python_poco.egg-info/requires.txt
python_poco.egg-info/top_level.txt