Metadata-Version: 1.1
Name: python-poco
Version: 0.1.0
Summary: Tool to integrate your Python app with Poco.
Home-page: https://github.com/johanmeiring/python-poco
Author: Johan Meiring
Author-email: johanmeiring@gmail.com
License: LICENSE
Platform: UNKNOWN
Classifier: Development Status :: 4 - Beta
Classifier: Intended Audience :: Developers
Classifier: License :: OSI Approved :: MIT License
Classifier: Programming Language :: Python
Classifier: Programming Language :: Python :: 2.7
Classifier: Programming Language :: Python :: 3.3
